ramlwrap/RamlWrap.py
ramlwrap/__init__.py
ramlwrap/views.py
ramlwrap/utils/__init__.py
ramlwrap/utils/exceptions.py
ramlwrap/utils/raml.py
ramlwrap/utils/validation.py
ramlwrap/utils/yaml_include_loader.py
ramlwrap-2.3.7.dist-info/LICENSE
ramlwrap-2.3.7.dist-info/METADATA
ramlwrap-2.3.7.dist-info/WHEEL
ramlwrap-2.3.7.dist-info/top_level.txt
ramlwrap-2.3.7.dist-info/RECORD
