Metadata-Version: 2.1
Name: ramlwrap
Version: 2.3.7
Summary: Raml API mapping toolkit for Django
Home-page: https://github.com/jmons/ramlwrap
Author: James Taylor
Author-email: jtaylor@cpicardgroup.com
License: MIT
Keywords: raml api django
Platform: UNKNOWN
Classifier: Development Status :: 5 - Production/Stable
Classifier: Intended Audience :: Developers
Classifier: Topic :: Software Development :: Code Generators
Classifier: License :: OSI Approved :: MIT License
Classifier: Programming Language :: Python :: 3
Classifier: Programming Language :: Python :: 3.5
Classifier: Programming Language :: Python :: 3.6
Classifier: Programming Language :: Python :: 3.7
Classifier: Programming Language :: Python :: 3.8
Requires-Dist: Django (>=2.0)
Requires-Dist: jsonschema (>=2.6.0)
Requires-Dist: pyyaml (>=3.12)
